airflow_xtended_api/__init__.py
airflow_xtended_api/config.py
airflow_xtended_api/exceptions.py
airflow_xtended_api/main.py
airflow_xtended_api/utils.py
airflow_xtended_api/api/__init__.py
airflow_xtended_api/api/api_setup.py
airflow_xtended_api/api/app.py
airflow_xtended_api/api/dag_utils.py
airflow_xtended_api/api/error_handlers.py
airflow_xtended_api/api/response.py
airflow_xtended_api/api/endpoints/__init__.py
airflow_xtended_api/api/endpoints/create_dag.py
airflow_xtended_api/api/endpoints/delete_dag.py
airflow_xtended_api/api/endpoints/deploy_dag.py
airflow_xtended_api/api/endpoints/kill_running_tasks.py
airflow_xtended_api/api/endpoints/purge_dags.py
airflow_xtended_api/api/endpoints/refresh_all_dags.py
airflow_xtended_api/api/endpoints/restart_failed_task.py
airflow_xtended_api/api/endpoints/run_task_instance.py
airflow_xtended_api/api/endpoints/scan_dags.py
airflow_xtended_api/api/endpoints/skip_task_instance.py
airflow_xtended_api/api/endpoints/sync_dags_from_mongo.py
airflow_xtended_api/api/endpoints/sync_dags_from_s3.py
airflow_xtended_api/api/endpoints/upload_file.py
airflow_xtended_api/core/__init__.py
airflow_xtended_api/core/mongo_sync.py
airflow_xtended_api/core/s3_sync.py
airflow_xtended_api/tasks/__init__.py
airflow_xtended_api/tasks/bg_task.py
airflow_xtended_api/tasks/scan_dags_bg_task.py
airflow_xtended_api/tasks/zip_bg_task.py
airflow_xtended_api/ui/__init__.py
airflow_xtended_api/ui/app_builder_view.py
airflow_xtended_api/ui/docs.py
airflow_xtended_api/ui/static/css/main.css
airflow_xtended_api/ui/static/js/main.js
airflow_xtended_api/ui/templates/doc_body.jinja.html
airflow_xtended_api/ui/templates/doc_head.jinja.html
airflow_xtended_api/ui/templates/doc_index.jinja.html
airflow_xtended_api-0.1.6.dist-info/LICENSE
airflow_xtended_api-0.1.6.dist-info/METADATA
airflow_xtended_api-0.1.6.dist-info/WHEEL
airflow_xtended_api-0.1.6.dist-info/entry_points.txt
airflow_xtended_api-0.1.6.dist-info/top_level.txt
airflow_xtended_api-0.1.6.dist-info/RECORD
