Metadata-Version: 2.1
Name: airflow_xtended_api
Version: 0.1.6
Summary: Exposes 'Xtended' Apache Airflow management capabilities via secure API
Home-page: https://github.com/anr007/airflow-xtended-api
Author: anr007
Author-email: 
License: GNU AGPLv3
Keywords: apache airflow,plugin,flask
Classifier: Development Status :: 4 - Beta
Classifier: Intended Audience :: Developers
Classifier: Topic :: Software Development :: Libraries
Classifier: Operating System :: OS Independent
Classifier: License :: OSI Approved :: GNU Affero General Public License v3 or later (AGPLv3+)
Classifier: Programming Language :: Python :: 3
Classifier: Programming Language :: Python :: 3.6
Classifier: Programming Language :: Python :: 3.8
Requires-Python: >=3.6
License-File: LICENSE
Requires-Dist: apache-airflow (>=2.8.0)
Requires-Dist: boto3 (>=1.17.97)
Requires-Dist: pymongo (>=3.11.4)
Requires-Dist: requests (>=2.25.1)
